bosa_connectors.cpython-311-darwin.so
bosa_connectors.pyi
bosa_connectors.build/.gitignore
gl_connector_binary-0.0.1b1.dist-info/METADATA
gl_connector_binary-0.0.1b1.dist-info/WHEEL
gl_connector_binary-0.0.1b1.dist-info/top_level.txt
gl_connector_binary-0.0.1b1.dist-info/RECORD
