Metadata-Version: 2.2
Name: gl-connector-binary
Version: 0.0.1b1
Summary: BOSA Connectors
Author-email: Bosa Engineers <bosa-eng@gdplabs.id>
Requires-Python: <3.14,>=3.11
Requires-Dist: pydantic-settings<3.0.0,>=2.7.1
Requires-Dist: pydantic<3.0.0,>=2.9.2
Requires-Dist: requests<3.0.0,>=2.31.0
Requires-Dist: langchain-core<1.0.0,>=0.3.65
Requires-Dist: legacy-cgi<3.0.0,>=2.6.3
Requires-Dist: urllib3<3.0.0,>=2.5.0
Requires-Dist: gllm-core-binary<0.4.0,>=0.3.10
Provides-Extra: dev
Requires-Dist: pytest<9.0.0,>=8.1.1; extra == "dev"
Requires-Dist: pre-commit<4.0.0,>=3.6.2; extra == "dev"
Requires-Dist: pytest-cov<6.0.0,>=5.0.0; extra == "dev"
Requires-Dist: pytest-asyncio<1.0.0,>=0.23.6; extra == "dev"
Requires-Dist: pydocstyle<7.0.0,>=6.3.0; extra == "dev"
Requires-Dist: ruff<1.0.0,>=0.9.9; extra == "dev"
Requires-Dist: mypy<2.0.0,>=1.11.2; extra == "dev"
Requires-Dist: coverage<8.0.0,>=7.10.2; extra == "dev"
